{
  "_class": "group",
  "booleanOperation": -1,
  "do_objectID": "222857DA-388B-41B1-A5ED-6F8AA24D3417",
  "exportOptions": {
    "_class": "exportOptions",
    "do_objectID": "35994522-E010-4355-B1E3-AF6832EE2EC5",
    "exportFormats": [
    ],
    "includedLayerIds": [
    ],
    "layerOptions": 0,
    "shouldTrim": false
  },
  "frame": {
    "_class": "rect",
    "constrainProportions": false,
    "do_objectID": "2CD0E55C-191C-4574-9DDA-AD2ABC97DC6A",
    "height": 65,
    "width": 202,
    "x": 0,
    "y": 37
  },
  "hasClickThrough": false,
  "isFixedToViewport": false,
  "isFlippedHorizontal": false,
  "isFlippedVertical": false,
  "isLocked": false,
  "isVisible": true,
  "layerListExpandedType": 2,
  "layers": [
    {
      "class": "text",
      "id": "30EF4ECF-A5EB-4ECF-A7EC-01F2018157CD"
    },
    {
      "class": "shapeGroup",
      "id": "621D04E6-8C30-42BD-97F6-7B0F7E6E4F8B"
    },
    {
      "class": "shapeGroup",
      "id": "EB57782B-DF63-44E0-9F13-7E5E5B3B8D4F"
    },
    {
      "class": "shapeGroup",
      "id": "8E303635-69A8-412E-A5A9-F70F2F6D1BDB"
    },
    {
      "class": "shapeGroup",
      "id": "3DFE6488-D365-4A08-93B4-40AA5A90493F"
    },
    {
      "class": "text",
      "id": "98D37000-33B5-41A5-A80E-EAF614434111"
    },
    {
      "class": "text",
      "id": "BC986D62-A342-43B4-B951-F545FBC3E2F0"
    }
  ],
  "name": "Group 3",
  "nameIsFixed": false,
  "resizingConstraint": 63,
  "resizingType": 0,
  "rotation": 0,
  "shouldBreakMaskChain": false,
  "style": {
    "_class": "style",
    "do_objectID": "16969E97-E8B6-488E-8695-CE1E1CB11F88",
    "endMarkerType": 0,
    "miterLimit": 10,
    "startMarkerType": 0,
    "windingRule": 1
  }
}