{
  "_class": "group",
  "booleanOperation": -1,
  "do_objectID": "08254660-F011-4589-906E-A385BE641262",
  "exportOptions": {
    "_class": "exportOptions",
    "exportFormats": [
    ],
    "includedLayerIds": [
    ],
    "layerOptions": 0,
    "shouldTrim": false
  },
  "frame": {
    "_class": "rect",
    "constrainProportions": false,
    "height": 51.00000000000004,
    "width": 156,
    "x": 0.7488151658767773,
    "y": 68.99999999999999
  },
  "hasClickThrough": false,
  "isFixedToViewport": false,
  "isFlippedHorizontal": false,
  "isFlippedVertical": false,
  "isLocked": false,
  "isVisible": true,
  "layerListExpandedType": 0,
  "layers": [
    {
      "class": "shapeGroup",
      "id": "3F5C11B2-BF24-441D-A4A0-ECA2491104F0"
    },
    {
      "class": "shapeGroup",
      "id": "C6114E9A-7AA6-4741-A12F-9E43F44A99DD"
    },
    {
      "class": "shapeGroup",
      "id": "9E77006A-C119-4A28-AA21-3D2BFF8C96EC"
    },
    {
      "class": "shapeGroup",
      "id": "20A13B42-5884-4175-AD97-81ACA2B96B4F"
    },
    {
      "class": "shapeGroup",
      "id": "D768C85D-43F3-4A7F-93B2-3FCE4641B7EA"
    }
  ],
  "name": "Thyme",
  "nameIsFixed": true,
  "resizingConstraint": 63,
  "resizingType": 0,
  "rotation": 0,
  "shouldBreakMaskChain": false,
  "style": {
    "_class": "style",
    "endMarkerType": 0,
    "miterLimit": 10,
    "startMarkerType": 0,
    "windingRule": 1
  }
}