{
  "_class": "bitmap",
  "booleanOperation": -1,
  "clippingMask": "{{0, 0}, {1, 1}}",
  "do_objectID": "22505DDC-E655-4548-951F-669608948AEE",
  "exportOptions": {
    "_class": "exportOptions",
    "do_objectID": "DDEBEC8C-19BF-4702-AA9B-D6145F2A6E8A",
    "exportFormats": [
    ],
    "includedLayerIds": [
    ],
    "layerOptions": 0,
    "shouldTrim": false
  },
  "fillReplacesImage": false,
  "frame": {
    "_class": "rect",
    "constrainProportions": true,
    "do_objectID": "E9FF7598-D72E-48B8-B90F-308CB2478083",
    "height": 820.4011299435028,
    "width": 1230.361445783133,
    "x": -202.469879518072,
    "y": -212.1751412429376
  },
  "image": {
    "_class": "MSJSONFileReference",
    "_ref": "images/9f95a32e16582d39fe49a579123c0f92d6e73ce1.png",
    "_ref_class": "MSImageData"
  },
  "intendedDPI": 72,
  "isFixedToViewport": false,
  "isFlippedHorizontal": false,
  "isFlippedVertical": false,
  "isLocked": false,
  "isVisible": true,
  "layerListExpandedType": 0,
  "name": "rawpixel-735373-unsplash",
  "nameIsFixed": false,
  "resizingConstraint": 63,
  "resizingType": 0,
  "rotation": 0,
  "shouldBreakMaskChain": false,
  "style": {
    "_class": "style",
    "blur": {
      "_class": "blur",
      "center": "{0.5, 0.5}",
      "do_objectID": "22E275D6-7378-4D47-8D3C-3495EF46F47E",
      "isEnabled": false,
      "motionAngle": 0,
      "radius": 13.365,
      "type": 0
    },
    "do_objectID": "F0FAB011-8849-4CA1-A918-DBBB5D1A3E2C",
    "endMarkerType": 0,
    "miterLimit": 10,
    "startMarkerType": 0,
    "windingRule": 1
  }
}