{
  "_class": "shapePath",
  "booleanOperation": -1,
  "do_objectID": "7B6AC231-C253-44DD-B4B3-11926EFD0E82",
  "edited": true,
  "exportOptions": {
    "_class": "exportOptions",
    "do_objectID": "1FBDDF92-3774-4FBA-9C52-FBC415551CA5",
    "exportFormats": [
    ],
    "includedLayerIds": [
    ],
    "layerOptions": 0,
    "shouldTrim": false
  },
  "frame": {
    "_class": "rect",
    "constrainProportions": false,
    "do_objectID": "2281EB33-B7AC-4A97-8FFC-1109350CC734",
    "height": 25.18031343283581,
    "width": 3.793699507389163,
    "x": 1.227733090885718,
    "y": 1.171253731343281
  },
  "isClosed": true,
  "isFixedToViewport": false,
  "isFlippedHorizontal": false,
  "isFlippedVertical": false,
  "isLocked": false,
  "isVisible": true,
  "layerListExpandedType": 0,
  "name": "Path",
  "nameIsFixed": false,
  "pointRadiusBehaviour": 1,
  "points": [
    {
      "_class": "curvePoint",
      "cornerRadius": 0,
      "curveFrom": "{0.43403179500364214, 0}",
      "curveMode": 1,
      "curveTo": "{0.43403179500364214, 0}",
      "hasCurveFrom": false,
      "hasCurveTo": false,
      "point": "{0.43403179500364214, 0}"
    },
    {
      "_class": "curvePoint",
      "cornerRadius": 0,
      "curveFrom": "{1, 1}",
      "curveMode": 1,
      "curveTo": "{1, 1}",
      "hasCurveFrom": false,
      "hasCurveTo": false,
      "point": "{1, 1}"
    },
    {
      "_class": "curvePoint",
      "cornerRadius": 0,
      "curveFrom": "{0.73029952436045753, 1}",
      "curveMode": 1,
      "curveTo": "{0.73029952436045753, 1}",
      "hasCurveFrom": false,
      "hasCurveTo": false,
      "point": "{0.73029952436045753, 1}"
    },
    {
      "_class": "curvePoint",
      "cornerRadius": 0,
      "curveFrom": "{0, 0}",
      "curveMode": 1,
      "curveTo": "{0, 0}",
      "hasCurveFrom": false,
      "hasCurveTo": false,
      "point": "{0, 0}"
    }
  ],
  "resizingConstraint": 63,
  "resizingType": 0,
  "rotation": 0,
  "shouldBreakMaskChain": false
}