{
  "_class": "group",
  "booleanOperation": -1,
  "do_objectID": "7B661254-3BC0-466A-A0BE-A61C1360675B",
  "exportOptions": {
    "_class": "exportOptions",
    "do_objectID": "B2D0A453-3737-4ECE-BEE5-23AF4F08ECE2",
    "exportFormats": [
    ],
    "includedLayerIds": [
    ],
    "layerOptions": 0,
    "shouldTrim": false
  },
  "frame": {
    "_class": "rect",
    "constrainProportions": false,
    "do_objectID": "1BE817DA-EEB6-4ECC-BBAC-8B75D5270922",
    "height": 7,
    "width": 226,
    "x": 0,
    "y": 175.5
  },
  "hasClickThrough": false,
  "isFixedToViewport": false,
  "isFlippedHorizontal": false,
  "isFlippedVertical": false,
  "isLocked": false,
  "isVisible": true,
  "layerListExpandedType": 0,
  "layers": [
    {
      "class": "shapeGroup",
      "id": "79570796-BC9F-4B89-9828-C9CBCF23C93D"
    },
    {
      "class": "shapeGroup",
      "id": "E1DCB5CA-9897-4BAD-8EE2-583D0F10CFA5"
    }
  ],
  "name": "Group 3",
  "nameIsFixed": false,
  "resizingConstraint": 63,
  "resizingType": 0,
  "rotation": 0,
  "shouldBreakMaskChain": false,
  "style": {
    "_class": "style",
    "blur": {
      "_class": "blur",
      "center": "{0.5, 0.5}",
      "do_objectID": "122E8C26-75E4-4864-AC93-B3DBA3593FAF",
      "isEnabled": false,
      "motionAngle": 0,
      "radius": 8,
      "type": 0
    },
    "do_objectID": "F02F3DB8-A45C-4BCE-A8C6-2F7AA7D4DAEC",
    "endMarkerType": 0,
    "miterLimit": 10,
    "startMarkerType": 0,
    "windingRule": 1
  }
}