{
  "_class": "shapeGroup",
  "booleanOperation": -1,
  "clippingMaskMode": 0,
  "do_objectID": "D606919D-40C0-494A-9D13-563B1988DE2F",
  "exportOptions": {
    "_class": "exportOptions",
    "do_objectID": "FC74A856-32DD-4E34-9868-ED0B6EA23615",
    "exportFormats": [
    ],
    "includedLayerIds": [
    ],
    "layerOptions": 0,
    "shouldTrim": false
  },
  "frame": {
    "_class": "rect",
    "constrainProportions": false,
    "do_objectID": "5348CFA8-8E2C-4CE8-9077-9798046162B2",
    "height": 42.84826430079917,
    "width": 37.81041411923329,
    "x": 0.05598994267744252,
    "y": 0.03368388660568563
  },
  "hasClickThrough": false,
  "hasClippingMask": false,
  "isFixedToViewport": false,
  "isFlippedHorizontal": false,
  "isFlippedVertical": false,
  "isLocked": false,
  "isVisible": true,
  "layerListExpandedType": 1,
  "layers": [
    {
      "class": "shapePath",
      "id": "E68249C1-1EC7-4367-B705-0FE4FD49F23E"
    },
    {
      "class": "shapePath",
      "id": "671059ED-17A4-4EC0-8032-D791B73DE49B"
    },
    {
      "class": "shapePath",
      "id": "A2B72E82-541F-44D4-B4DE-E9C00C95FF73"
    }
  ],
  "name": "Fill 3",
  "nameIsFixed": false,
  "resizingConstraint": 63,
  "resizingType": 0,
  "rotation": 0,
  "shouldBreakMaskChain": false,
  "style": {
    "_class": "style",
    "blur": {
      "_class": "blur",
      "center": "{0.5, 0.5}",
      "do_objectID": "6AF29909-7EB2-4F17-9A8C-A9A216EA7A9E",
      "isEnabled": false,
      "motionAngle": 0,
      "radius": 3.25,
      "type": 0
    },
    "do_objectID": "E1B174B5-0B89-46A6-AE03-340638EF096E",
    "endMarkerType": 0,
    "fills": [
      {
        "_class": "fill",
        "color": {
          "_class": "color",
          "alpha": 1,
          "blue": 0.2705882352941176,
          "green": 0.6941176470588235,
          "red": 0.396078431372549
        },
        "fillType": 0,
        "isEnabled": true,
        "noiseIndex": 0,
        "noiseIntensity": 0,
        "patternFillType": 1,
        "patternTileScale": 1
      }
    ],
    "miterLimit": 10,
    "startMarkerType": 0,
    "windingRule": 1
  },
  "windingRule": 1
}