{
  "_class": "group",
  "booleanOperation": -1,
  "do_objectID": "94A9BB26-4520-45B9-8161-EBC1F7E06EA2",
  "exportOptions": {
    "_class": "exportOptions",
    "exportFormats": [
    ],
    "includedLayerIds": [
    ],
    "layerOptions": 0,
    "shouldTrim": false
  },
  "frame": {
    "_class": "rect",
    "constrainProportions": false,
    "height": 116.1,
    "width": 92.00000000000001,
    "x": 0,
    "y": 0.01349999999998772
  },
  "hasClickThrough": false,
  "isFixedToViewport": false,
  "isFlippedHorizontal": false,
  "isFlippedVertical": false,
  "isLocked": false,
  "isVisible": true,
  "layerListExpandedType": 0,
  "layers": [
    {
      "class": "shapeGroup",
      "id": "BE8F6465-0F27-463D-8612-1AFC0E1B0D3B"
    },
    {
      "class": "shapeGroup",
      "id": "112289F3-0D9F-466E-A68C-F02B7F4E51B2"
    }
  ],
  "name": "Group 3",
  "nameIsFixed": false,
  "resizingConstraint": 63,
  "resizingType": 0,
  "rotation": 0,
  "shouldBreakMaskChain": false,
  "style": {
    "_class": "style",
    "blur": {
      "_class": "blur",
      "center": "{0.5, 0.5}",
      "isEnabled": false,
      "motionAngle": 0,
      "radius": 4.5,
      "type": 0
    },
    "endMarkerType": 0,
    "miterLimit": 10,
    "startMarkerType": 0,
    "windingRule": 1
  }
}