{
  "_class": "text",
  "attributedString": {
    "_class": "attributedString",
    "attributes": [
      {
        "_class": "stringAttribute",
        "attributes": {
          "MSAttributedStringColorAttribute": {
            "_class": "color",
            "alpha": 1,
            "blue": 0.3607843137254902,
            "green": 0.3490196078431372,
            "red": 0.3450980392156863
          },
          "MSAttributedStringFontAttribute": {
            "_class": "fontDescriptor",
            "attributes": {
              "name": "HelveticaNeue-Medium",
              "size": 32
            }
          },
          "kerning": 0,
          "paragraphStyle": {
            "_class": "paragraphStyle",
            "alignment": 0,
            "allowsDefaultTighteningForTruncation": 0
          },
          "textStyleVerticalAlignmentKey": 1
        },
        "length": 13,
        "location": 0
      }
    ],
    "string": "Section Title"
  },
  "automaticallyDrawOnUnderlyingPath": false,
  "booleanOperation": -1,
  "do_objectID": "507646B5-161D-416B-AC7B-1E95C8AC0550",
  "dontSynchroniseWithSymbol": false,
  "exportOptions": {
    "_class": "exportOptions",
    "do_objectID": "3BB3B95A-59A7-407F-A1EA-3FFC38814601",
    "exportFormats": [
    ],
    "includedLayerIds": [
    ],
    "layerOptions": 0,
    "shouldTrim": false
  },
  "frame": {
    "_class": "rect",
    "constrainProportions": false,
    "do_objectID": "9807E01D-3CD3-4FF9-82F4-37B4E5D3E8D2",
    "height": 42.25469728601252,
    "width": 567,
    "x": 49,
    "y": 28.81002087682672
  },
  "glyphBounds": "{{1, 7}, {183, 25}}",
  "isFixedToViewport": false,
  "isFlippedHorizontal": false,
  "isFlippedVertical": false,
  "isLocked": false,
  "isVisible": true,
  "layerListExpandedType": 0,
  "lineSpacingBehaviour": 2,
  "name": "Section Title",
  "nameIsFixed": false,
  "resizingConstraint": 63,
  "resizingType": 0,
  "rotation": 0,
  "shouldBreakMaskChain": false,
  "style": {
    "_class": "style",
    "blur": {
      "_class": "blur",
      "center": "{0.5, 0.5}",
      "do_objectID": "78457050-D9DD-415D-801F-9EB9043438A8",
      "isEnabled": false,
      "motionAngle": 0,
      "radius": 13.33333333333333,
      "type": 0
    },
    "do_objectID": "0813FDAE-95C6-4937-A339-A25CC5614A8F",
    "endMarkerType": 0,
    "miterLimit": 10,
    "sharedObjectID": "6C4044A6-B098-421B-94D9-301DEFC85A6E",
    "startMarkerType": 0,
    "textStyle": {
      "_class": "textStyle",
      "do_objectID": "A55F068F-E958-4DE2-9784-ED129FF167B0",
      "encodedAttributes": {
        "MSAttributedStringColorAttribute": {
          "_class": "color",
          "alpha": 1,
          "blue": 0.3607843137254902,
          "green": 0.3490196078431372,
          "red": 0.3450980392156863
        },
        "MSAttributedStringFontAttribute": {
          "_class": "fontDescriptor",
          "attributes": {
            "name": "HelveticaNeue-Medium",
            "size": 32
          }
        },
        "kerning": 0,
        "paragraphStyle": {
          "_class": "paragraphStyle",
          "alignment": 0,
          "allowsDefaultTighteningForTruncation": 0
        },
        "textStyleVerticalAlignmentKey": 1
      },
      "verticalAlignment": 0
    },
    "windingRule": 1
  },
  "textBehaviour": 2
}