{
  "_class": "symbolInstance",
  "booleanOperation": -1,
  "do_objectID": "BEB2A576-E601-49FD-AB51-EF67F40D347E",
  "exportOptions": {
    "_class": "exportOptions",
    "do_objectID": "05904840-B5F9-4CA2-9F5A-25B70273F0CC",
    "exportFormats": [
    ],
    "includedLayerIds": [
    ],
    "layerOptions": 0,
    "shouldTrim": false
  },
  "frame": {
    "_class": "rect",
    "constrainProportions": false,
    "do_objectID": "06FB8DB5-624C-4A8C-BFD6-7B4F6B9A8027",
    "height": 54,
    "width": 144,
    "x": 378,
    "y": 1002
  },
  "horizontalSpacing": 0,
  "isFixedToViewport": false,
  "isFlippedHorizontal": false,
  "isFlippedVertical": false,
  "isLocked": false,
  "isVisible": true,
  "layerListExpandedType": 0,
  "name": "Filter Button Copy 4",
  "nameIsFixed": false,
  "overrideValues": [
    {
      "_class": "overrideValue",
      "do_objectID": "FF889F58-F413-4932-A8E6-2954AA869E16",
      "overrideName": "26D52629-9084-4A19-8630-F3FB164FA712_stringValue",
      "value": "American"
    }
  ],
  "resizingConstraint": 63,
  "resizingType": 0,
  "rotation": 0,
  "scale": 1,
  "shouldBreakMaskChain": false,
  "style": {
    "_class": "style",
    "do_objectID": "F557508D-1CAA-44EF-B4F1-3DF97398740C",
    "endMarkerType": 0,
    "miterLimit": 10,
    "startMarkerType": 0,
    "windingRule": 1
  },
  "symbolID": "FF576506-5D2F-4E7E-94F7-0741483A5320",
  "verticalSpacing": 0
}