{
  "_class": "bitmap",
  "booleanOperation": -1,
  "clippingMask": "{{0, 0}, {1, 1}}",
  "do_objectID": "B2E5F2B0-2AC5-4F94-B7A1-325A29716E2C",
  "exportOptions": {
    "_class": "exportOptions",
    "do_objectID": "89B8B0F0-1F79-4FFB-AC58-4700A6224B58",
    "exportFormats": [
    ],
    "includedLayerIds": [
    ],
    "layerOptions": 0,
    "shouldTrim": false
  },
  "fillReplacesImage": false,
  "frame": {
    "_class": "rect",
    "constrainProportions": true,
    "do_objectID": "6FD1B183-B291-4A92-94C4-11B6A7BF6538",
    "height": 36,
    "width": 122,
    "x": 434,
    "y": 227
  },
  "image": {
    "_class": "MSJSONFileReference",
    "_ref": "images/5aa9b41cb4c3ea61214940a059d0769499c9dabb.png",
    "_ref_class": "MSImageData"
  },
  "intendedDPI": 72,
  "isFixedToViewport": false,
  "isFlippedHorizontal": false,
  "isFlippedVertical": false,
  "isLocked": false,
  "isVisible": true,
  "layerListExpandedType": 0,
  "name": "apple-app-store-icon",
  "nameIsFixed": false,
  "resizingConstraint": 63,
  "resizingType": 0,
  "rotation": 0,
  "shouldBreakMaskChain": false,
  "style": {
    "_class": "style",
    "blur": {
      "_class": "blur",
      "center": "{0.5, 0.5}",
      "do_objectID": "7755E859-C63D-4A64-980F-071C928460D8",
      "isEnabled": false,
      "motionAngle": 0,
      "radius": 6,
      "type": 0
    },
    "do_objectID": "D9A6BBD0-41D3-4C46-8428-95B9995598FD",
    "endMarkerType": 0,
    "miterLimit": 10,
    "startMarkerType": 0,
    "windingRule": 1
  }
}