{
  "_class": "symbolInstance",
  "booleanOperation": -1,
  "do_objectID": "A03F5DF2-AEF1-4EFE-A4F6-A439A1E4397E",
  "exportOptions": {
    "_class": "exportOptions",
    "do_objectID": "533AAD85-37BC-451B-BB5D-5CA3C38E72D6",
    "exportFormats": [
    ],
    "includedLayerIds": [
    ],
    "layerOptions": 0,
    "shouldTrim": false
  },
  "frame": {
    "_class": "rect",
    "constrainProportions": false,
    "do_objectID": "983071A9-0191-4F76-82F2-298E8886FAE5",
    "height": 464,
    "width": 768,
    "x": 0,
    "y": 2928
  },
  "horizontalSpacing": 0,
  "isFixedToViewport": false,
  "isFlippedHorizontal": false,
  "isFlippedVertical": false,
  "isLocked": false,
  "isVisible": true,
  "layerListExpandedType": 0,
  "name": "Homepage Info Group (Image on Right) Colored Background",
  "nameIsFixed": false,
  "overrideValues": [
  ],
  "resizingConstraint": 63,
  "resizingType": 0,
  "rotation": 0,
  "scale": 1,
  "shouldBreakMaskChain": false,
  "style": {
    "_class": "style",
    "do_objectID": "F998777B-2387-4E46-AE00-CABEF6EFCC58",
    "endMarkerType": 0,
    "miterLimit": 10,
    "startMarkerType": 0,
    "windingRule": 1
  },
  "symbolID": "B96D0107-89EE-4B37-B7E2-B53046379975",
  "verticalSpacing": 0
}