{
  "_class": "bitmap",
  "booleanOperation": -1,
  "clippingMask": "{{0, 0}, {1, 1}}",
  "do_objectID": "ACD92F9B-CA5A-40B5-B08E-D937AAD8CF0B",
  "exportOptions": {
    "_class": "exportOptions",
    "do_objectID": "CF420C9D-8564-47F9-A5F2-2B2C91A6A676",
    "exportFormats": [
    ],
    "includedLayerIds": [
    ],
    "layerOptions": 0,
    "shouldTrim": false
  },
  "fillReplacesImage": false,
  "frame": {
    "_class": "rect",
    "constrainProportions": true,
    "do_objectID": "2F20D965-0D2A-4607-9CC6-4324F00FF25C",
    "height": 353,
    "width": 471,
    "x": -39,
    "y": 0
  },
  "image": {
    "_class": "MSJSONFileReference",
    "_ref": "images/4313d031e8abaf203af7aae66f1454bee19e9399.png",
    "_ref_class": "MSImageData"
  },
  "intendedDPI": 72,
  "isFixedToViewport": false,
  "isFlippedHorizontal": false,
  "isFlippedVertical": false,
  "isLocked": false,
  "isVisible": true,
  "layerListExpandedType": 0,
  "name": "great",
  "nameIsFixed": false,
  "resizingConstraint": 63,
  "resizingType": 0,
  "rotation": 0,
  "shouldBreakMaskChain": false,
  "style": {
    "_class": "style",
    "do_objectID": "FCBDCA40-6405-4519-882A-029D108B4FAD",
    "endMarkerType": 0,
    "miterLimit": 10,
    "startMarkerType": 0,
    "windingRule": 1
  }
}