{
  "_class": "oval",
  "booleanOperation": -1,
  "do_objectID": "4036D044-55AE-4C01-9481-DA991CE04D74",
  "edited": false,
  "exportOptions": {
    "_class": "exportOptions",
    "do_objectID": "D84E761B-DA36-48CE-95C5-D38FE4649324",
    "exportFormats": [
    ],
    "includedLayerIds": [
    ],
    "layerOptions": 0,
    "shouldTrim": false
  },
  "frame": {
    "_class": "rect",
    "constrainProportions": false,
    "do_objectID": "4DE1A16C-9041-4B99-9373-3311F64FE567",
    "height": 11.2,
    "width": 11.2,
    "x": 0,
    "y": 0
  },
  "isClosed": true,
  "isFixedToViewport": false,
  "isFlippedHorizontal": false,
  "isFlippedVertical": false,
  "isLocked": false,
  "isVisible": true,
  "layerListExpandedType": 0,
  "name": "Path",
  "nameIsFixed": false,
  "pointRadiusBehaviour": 1,
  "points": [
    {
      "_class": "curvePoint",
      "cornerRadius": 0,
      "curveFrom": "{0.77614237490000004, 1}",
      "curveMode": 2,
      "curveTo": "{0.22385762510000001, 1}",
      "hasCurveFrom": true,
      "hasCurveTo": true,
      "point": "{0.5, 1}"
    },
    {
      "_class": "curvePoint",
      "cornerRadius": 0,
      "curveFrom": "{1, 0.22385762510000001}",
      "curveMode": 2,
      "curveTo": "{1, 0.77614237490000004}",
      "hasCurveFrom": true,
      "hasCurveTo": true,
      "point": "{1, 0.5}"
    },
    {
      "_class": "curvePoint",
      "cornerRadius": 0,
      "curveFrom": "{0.22385762510000001, 0}",
      "curveMode": 2,
      "curveTo": "{0.77614237490000004, 0}",
      "hasCurveFrom": true,
      "hasCurveTo": true,
      "point": "{0.5, 0}"
    },
    {
      "_class": "curvePoint",
      "cornerRadius": 0,
      "curveFrom": "{0, 0.77614237490000004}",
      "curveMode": 2,
      "curveTo": "{0, 0.22385762510000001}",
      "hasCurveFrom": true,
      "hasCurveTo": true,
      "point": "{0, 0.5}"
    }
  ],
  "resizingConstraint": 63,
  "resizingType": 0,
  "rotation": 0,
  "shouldBreakMaskChain": false
}